regression/__init__.py
regression/linear_regression.py
my_linear_regression-0.1.0.dist-info/LICENSE.txt
my_linear_regression-0.1.0.dist-info/METADATA
my_linear_regression-0.1.0.dist-info/WHEEL
my_linear_regression-0.1.0.dist-info/top_level.txt
my_linear_regression-0.1.0.dist-info/RECORD
