Metadata-Version: 2.1
Name: my_linear_regression
Version: 0.1.0
Summary: A simple linear regression model implemented from scratch.
Home-page: http://pypi.python.org/pypi/my_linear_regression/
Author: Haitham
Author-email: your_email@example.com
License: LICENSE.txt
License-File: LICENSE.txt
